translatesubs/__init__.py
translatesubs/main.py
translatesubs/managers/__init__.py
translatesubs/managers/language_manager.py
translatesubs/managers/subs_manager.py
translatesubs/translators/__init__.py
translatesubs/translators/google_trans_new.py
translatesubs/translators/googletrans.py
translatesubs/translators/itranslator.py
translatesubs/translators/language.py
translatesubs/translators/translated.py
translatesubs/utils/__init__.py
translatesubs/utils/constants.py
translatesubs/utils/tools.py
translatesubs-0.2.4.dist-info/LICENSE
translatesubs-0.2.4.dist-info/METADATA
translatesubs-0.2.4.dist-info/WHEEL
translatesubs-0.2.4.dist-info/entry_points.txt
translatesubs-0.2.4.dist-info/top_level.txt
translatesubs-0.2.4.dist-info/RECORD
