Metadata-Version: 2.1
Name: translatesubs
Version: 0.2.4
Summary: It is a tool to translate subtitles into any language, that is supported by google translator
Home-page: https://github.com/Montvydas/translatesubs
Download-URL: https://github.com/Montvydas/translatesubs/archive/v_0.2.4.tar.gz
Author: Montvydas Klumbys
Author-email: montvydas.klumbys@gmail.com
License: Apache-2.0
Keywords: SUBTITLES,TRANSLATE
Classifier: Development Status :: 4 - Beta
Classifier: Programming Language :: Python :: 3
Classifier: License :: OSI Approved :: Apache Software License 
Classifier: Operating System :: OS Independent
Classifier: Topic :: Multimedia :: Video
Requires-Python: >=3.6
License-File: LICENSE
Requires-Dist: pysubs2 (==1.6.0)
Requires-Dist: googletrans (==3.1.0a0)
Requires-Dist: google-trans-new (==1.1.9)
Requires-Dist: chardet (==3.0.4)
Requires-Dist: requests (==2.28.2)
